embedding_reader/__init__.py
embedding_reader/embedding_reader.py
embedding_reader/get_file_list.py
embedding_reader/numpy_reader.py
embedding_reader/parquet_numpy_reader.py
embedding_reader/parquet_reader.py
embedding_reader/piece_builder.py
embedding_reader-1.8.1.data/data/README.md
embedding_reader-1.8.1.dist-info/LICENSE
embedding_reader-1.8.1.dist-info/METADATA
embedding_reader-1.8.1.dist-info/WHEEL
embedding_reader-1.8.1.dist-info/top_level.txt
embedding_reader-1.8.1.dist-info/RECORD
