Metadata-Version: 2.1
Name: embedding-reader
Version: 1.8.1
Summary: A python template
Home-page: https://github.com/rom1504/embedding-reader
Author: Romain Beaumont
Author-email: romain.rom1@gmail.com
License: MIT
Keywords: machine learning
Platform: UNKNOWN
Classifier: Development Status :: 4 - Beta
Classifier: Intended Audience :: Developers
Classifier: Topic :: Scientific/Engineering :: Artificial Intelligence
Classifier: License :: OSI Approved :: MIT License
Classifier: Programming Language :: Python :: 3.10
Classifier: Programming Language :: Python :: 3.11
Classifier: Programming Language :: Python :: 3.12
Requires-Dist: tqdm<5,>=4.62.3
Requires-Dist: fsspec>=2022.1.0
Requires-Dist: numpy>=1.19.5
Requires-Dist: pandas<3,>=1.1.5
Requires-Dist: pyarrow<30,>=6.0.1
